csscolors/__init__.py
csscolors-1.0.3.dist-info/METADATA
csscolors-1.0.3.dist-info/WHEEL
csscolors-1.0.3.dist-info/top_level.txt
csscolors-1.0.3.dist-info/RECORD
