Metadata-Version: 2.1
Name: csscolors
Version: 1.0.3
Summary: CSS Colors in hex color codes.
Home-page: https://github.com/jakkes/py-csscolors
Author: Jakob Stigenberg
License: UNKNOWN
Platform: UNKNOWN
Classifier: Programming Language :: Python :: 3
Classifier: License :: OSI Approved :: MIT License
Classifier: Operating System :: OS Independent
Requires-Python: >=3.5
